mchnpkg-0.4.6.dist-info/METADATA
mchnpkg-0.4.6.dist-info/WHEEL
mchnpkg/__init__.py
mchnpkg/_core.abi3.so
mchnpkg/_core.pyi
mchnpkg/differential/__init__.py
mchnpkg/differential/discrete.py
mchnpkg/differential/matrix.ipynb
mchnpkg/distributions/Untitled-1.ipynb
mchnpkg/distributions/__init__.py
mchnpkg/distributions/colab.ipynb
mchnpkg/distributions/cvdistributions.py
mchnpkg/matrix/__init__.py
mchnpkg/matrix/elementary.py
mchnpkg/model/__init__.py
mchnpkg/model/cauchy_statsmodels.py
mchnpkg/model/logit.py
mchnpkg/model/regression.py
mchnpkg/py.typed
mchnpkg-0.4.6.dist-info/RECORD
