Metadata-Version: 2.4
Name: mchnpkg
Version: 0.4.6
Requires-Dist: matplotlib>=3.10.6
Requires-Dist: numpy>=2.3.3
Requires-Dist: scipy>=1.16.2
Requires-Dist: torch>=2.8.0
Requires-Dist: twine>=6.2.0
Summary: Add your description here
Author-email: helpmehelpgh <helpmehelp44@gmail.com>
Requires-Python: >=3.12
